sfu_torchac/__init__.py
sfu_torchac/backend/torchac.cpp
sfu_torchac/torchac.py
torchac_backend_cpu.cpython-310-x86_64-linux-gnu.so
sfu_torchac-0.0.2.dist-info/LICENSE
sfu_torchac-0.0.2.dist-info/WHEEL
sfu_torchac-0.0.2.dist-info/METADATA
sfu_torchac-0.0.2.dist-info/RECORD
